[
    {
        "productId": 1,
        "productName": "Project Management Software",
        "scrumMasterName": "Mason Blue",
        "productOwnerName": "Jon Doe",
        "Developers": [
            "Alice Brown",
            "Bob Johnson",
            "Charlie Lee",
            "David Kim",
            "Emily Chen"
        ],
        "startDate": "2022/01/01",
        "methodology": "Agile"
    },
    {
        "productId": 2,
        "productName": "E-commerce Website",
        "scrumMasterName": "Steven Garcia",
        "productOwnerName": "Jane Doe",
        "Developers": [
            "Alice Brown",
            "Bob Johnson",
            "David Kim",
            "Emily Chen",
            "George Lee"
        ],
        "startDate": "2022/02/01",
        "methodology": "Scrum"
    },
    {
        "productId": 3,
        "productName": "Mobile App",
        "scrumMasterName": "Lila Nguyen",
        "productOwnerName": "Tom Jones",
        "Developers": [
            "Alice Brown",
            "Charlie Lee",
            "David Kim",
            "Emily Chen",
            "Fred Clark"
        ],
        "startDate": "2022/03/01",
        "methodology": "Kanban"
    },
    {
        "productId": 4,
        "productName": "Online Store",
        "scrumMasterName": "Brad Pickering",
        "productOwnerName": "Sarah Davis",
        "Developers": [
            "Bob Johnson",
            "Charlie Lee",
            "David Kim",
            "Emily Chen",
            "George Lee"
        ],
        "startDate": "2022/04/01",
        "methodology": "Agile"
    },
    {
        "productId": 5,
        "productName": "Social Media Platform",
        "productOwnerName": "Megan Taylor",
        "Developers": [
            "Alice Brown",
            "Charlie Lee",
            "David Kim",
            "Emily Chen",
            "Fred Clark"
        ],
        "scrumMasterName": "Frank Wilson",
        "startDate": "2022/05/01",
        "methodology": "Scrum"
    },
    {
        "productId": 6,
        "productName": "HR Management Software",
        "scrumMasterName": "Elijah Kim",
        "productOwnerName": "David Adams",
        "Developers": [
            "Bob Johnson",
            "Charlie Lee",
            "David Kim",
            "Emily Chen",
            "George Lee"
        ],
        "startDate": "2022/06/01",
        "methodology": "Kanban"
    },
    {
        "productId": 7,
        "productName": "Online Learning Platform",
        "scrumMasterName": "Avery Mitchell",
        "productOwnerName": "Anna Lee",
        "Developers": [
            "Alice Brown",
            "Charlie Lee",
            "David Kim",
            "Emily Chen",
            "George Lee"
        ],
        "startDate": "2022/07/01",
        "methodology": "Agile"
    },
    {
        "productId": 8,
        "productName": "Fitness Tracking App",
        "scrumMasterName": "Logan Patel",
        "productOwnerName": "Mark Brown",
        "Developers": [
            "Alice Brown",
            "Bob Johnson",
            "Charlie Lee",
            "David Kim",
            "Emily Chen"
        ],
        "startDate": "2022/08/01",
        "methodology": "Scrum"
    },
    {
        "productId": 9,
        "productName": "E-learning App",
        "scrumMasterName": "Tom White",
        "productOwnerName": "Chris Green",
        "Developers": [
            "Alice Brown",
            "Charlie Lee",
            "David Kim",
            "Emily Chen",
            "Fred Clark"
        ],
        "startDate": "2022/09/01",
        "methodology": "Kanban"
    },
    {
        "productId": 10,
        "productName": "Online Marketplace",
        "scrumMasterName": "Oliver Lee",
        "productOwnerName": "Laura White",
        "Developers": [
            "Bob Johnson",
            "Charlie Lee",
            "David Kim",
            "Emily Chen",
            "George Lee"
        ],
        "startDate": "2022/10/01",
        "methodology": "Agile"
    },
    {
        "productId": 11,
        "productName": "Finance Management App",
        "scrumMasterName": "Ben Jamin",
        "productOwnerName": "Alex Kim",
        "Developers": [
            "Alice Brown",
            "Charlie Lee",
            "David Kim",
            "Emily Chen",
            "Fred Clark"
        ],
        "startDate": "2022/11/01",
        "methodology": "Scrum"
    },
    {
        "productId": 12,
        "productName": "Task Management Tool",
        "scrumMasterName": "Carter Davis",
        "productOwnerName": "Michael Davis",
        "Developers": [
            "Bob Johnson",
            "Charlie Lee",
            "David Kim",
            "Emily Chen",
            "George Lee"
        ],
        "startDate": "2022/12/01",
        "methodology": "Kanban"
    },
    {
        "productId": 13,
        "productName": "Travel Booking Website",
        "productOwnerName": "Samantha Lee",
        "Developers": [
            "Alice Brown",
            "Bob Johnson",
            "Charlie Lee",
            "David Kim",
            "Emily Chen"
        ],
        "scrumMasterName": "Frank Wilson",
        "startDate": "2023/01/01",
        "methodology": "Agile"
    },
    {
        "productId": 14,
        "productName": "Inventory Management System",
        "scrumMasterName": "Aria Robinson",
        "productOwnerName": "Timothy Jones",
        "Developers": [
            "Bob Johnson",
            "Charlie Lee",
            "David Kim",
            "Emily Chen",
            "George Lee"
        ],
        "startDate": "2023/02/01",
        "methodology": "Scrum"
    },
    {
        "productId": 15,
        "productName": "Real Estate Website",
        "scrumMasterName": "Noah Wright",
        "productOwnerName": "Emily Green",
        "Developers": [
            "Alice Brown",
            "Charlie Lee",
            "David Kim",
            "Emily Chen",
            "Fred Clark"
        ],
        "startDate": "2023/03/01",
        "methodology": "Kanban"
    },
    {
        "productId": 16,
        "productName": "Weather App",
        "scrumMasterName": "Harper Brown",
        "productOwnerName": "Erica Davis",
        "Developers": [
            "Bob Johnson",
            "Charlie Lee",
            "David Kim",
            "Emily Chen",
            "George Lee"
        ],
        "startDate": "2023/04/01",
        "methodology": "Agile"
    },
    {
        "productId": 17,
        "productName": "Social Media Platform",
        "scrumMasterName": "Tom White",
        "productOwnerName": "Ryan Kim",
        "Developers": [
            "Alice Brown",
            "Charlie Lee",
            "David Kim",
            "Emily Chen",
            "Fred Clark"
        ],
        "startDate": "2023/05/01",
        "methodology": "Scrum"
    },
    {
        "productId": 18,
        "productName": "Online Food Ordering System",
        "scrumMasterName": "Frank Wilson",
        "productOwnerName": "Jennifer Lee",
        "Developers": [
            "Bob Johnson",
            "Charlie Lee",
            "David Kim",
            "Emily Chen",
            "George Lee"
        ],
        "startDate": "2023/06/01",
        "methodology": "Kanban"
    },
    {
        "productId": 19,
        "productName": "Human Resource Management System",
        "scrumMasterName": "Tom White",
        "productOwnerName": "Sarah Smith",
        "Developers": [
            "Alice Brown",
            "Bob Johnson",
            "David Kim",
            "Emily Chen",
            "Fred Clark"
        ],
        "startDate": "2023/07/01",
        "methodology": "Agile"
    },
    {
        "productId": 20,
        "productName": "Online Booking System",
        "productOwnerName": "Daniel Wilson",
        "Developers": [
            "Charlie Lee",
            "David Kim",
            "Emily Chen",
            "Fred Clark",
            "George Lee"
        ],
        "scrumMasterName": "Frank Wilson",
        "startDate": "2023/08/01",
        "methodology": "Scrum"
    },
    {
        "productId": 21,
        "productName": "E-commerce Website",
        "productOwnerName": "Ava Brown",
        "Developers": [
            "Alice Brown",
            "Bob Johnson",
            "Charlie Lee",
            "David Kim",
            "Emily Chen"
        ],
        "scrumMasterName": "Frank Wilson",
        "startDate": "2023/09/01",
        "methodology": "Kanban"
    },
    {
        "productId": 22,
        "productName": "Project Management Tool",
        "productOwnerName": "Benjamin Davis",
        "Developers": [
            "Alice Brown",
            "Bob Johnson",
            "David Kim",
            "Emily Chen",
            "Fred Clark"
        ],
        "scrumMasterName": "Frank Wilson",
        "startDate": "2023/10/01",
        "methodology": "Agile"
    },
    {
        "productId": 23,
        "productName": "Fitness Tracker",
        "scrumMasterName": "Emma Zhang",
        "productOwnerName": "Maria Hernandez",
        "Developers": [
            "Charlie Lee",
            "David Kim",
            "Emily Chen",
            "Fred Clark",
            "George Lee"
        ],
        "startDate": "2023/11/01",
        "methodology": "Scrum"
    },
    {
        "productId": 24,
        "productName": "Online Marketplace",
        "productOwnerName": "Olivia Kim",
        "Developers": [
            "Alice Brown",
            "Bob Johnson",
            "Charlie Lee",
            "David Kim",
            "Emily Chen"
        ],
        "scrumMasterName": "Frank Wilson",
        "startDate": "2023/12/01",
        "methodology": "Kanban"
    },
    {
        "productId": 25,
        "productName": "Online Education Platform",
        "scrumMasterName": "Aria Robinson",
        "productOwnerName": "Thomas Garcia",
        "Developers": [
            "Bob Johnson",
            "Charlie Lee",
            "David Kim",
            "Emily Chen",
            "George Lee"
        ],
        "startDate": "2024/01/01",
        "methodology": "Agile"
    },
    {
        "productId": 26,
        "productName": "Customer Relationship Management System",
        "productOwnerName": "Sophia Brown",
        "Developers": [
            "Alice Brown",
            "Charlie Lee",
            "David Kim",
            "Emily Chen",
            "Fred Clark"
        ],
        "scrumMasterName": "Frank Wilson",
        "startDate": "2024/02/01",
        "methodology": "Scrum"
    },
    {
        "productId": 27,
        "productName": "Personal Finance App",
        "scrumMasterName": "Frank Wilson",
        "productOwnerName": "Joseph Martinez",
        "Developers": [
            "Bob Johnson",
            "Charlie Lee",
            "David Kim",
            "Emily Chen",
            "Brad Pickering"
        ],
        "startDate": "2024/03/01",
        "methodology": "Kanban"
    },
    {
        "productId": 28,
        "productName": "Medical Record Management System",
        "productOwnerName": "Isabella Davis",
        "Developers": [
            "Alice Brown",
            "Bob Johnson",
            "Charlie Lee",
            "David Kim",
            "Emily Chen"
        ],
        "scrumMasterName": "Frank Wilson",
        "startDate": "2024/04/01",
        "methodology": "Agile"
    },
    {
        "productId": 29,
        "productName": "Travel Planner",
        "scrumMasterName": "Elijah Kim",
        "productOwnerName": "William Rodriguez",
        "Developers": [
            "Charlie Lee",
            "David Kim",
            "Emily Chen",
            "Fred Clark",
            "George Lee"
        ],
        "startDate": "2024/03/01",
        "methodology": "Agile"
    },
    {
        "productId": 30,
        "productName": "Online Legal Document Generator",
        "scrumMasterName": "Frank Smith",
        "productOwnerName": "Ava Hernandez",
        "Developers": [
            "Alice Brown",
            "Bob Johnson",
            "Charlie Lee",
            "David Kim",
            "Emily Chen"
        ],
        "startDate": "2024/06/01",
        "methodology": "Scrum"
    },
    {
        "productName": "Camping Website",
        "scrumMasterName": "Brad Pickering",
        "productOwnerName": "Brad",
        "Developers": [
            "Jeff Rey",
            "Steve N"
        ],
        "startDate": "2023/03/31",
        "methodology": "Agile",
        "productId": 31
    }
]